cli/get_config.py
cli/pe_cli.py
pattan_sendgrid/PattanEmail.py
pattan_sendgrid/__init__.py
pattan_sendgrid/exceptions.py
pattan_sendgrid/models.py
pattan_sendgrid-2.1.0.dist-info/licenses/LICENSE
pattan_sendgrid-2.1.0.dist-info/METADATA
pattan_sendgrid-2.1.0.dist-info/WHEEL
pattan_sendgrid-2.1.0.dist-info/entry_points.txt
pattan_sendgrid-2.1.0.dist-info/top_level.txt
pattan_sendgrid-2.1.0.dist-info/RECORD
