Metadata-Version: 2.4
Name: pattan-sendgrid
Version: 2.1.0
Summary: Manage Sendgrid assets
Author-email: Markus Weltin <mweltin@pattan.net>, Don Rea <drea@pattan.net>
Maintainer-email: Markus Weltin <mweltin@pattan.net>
Project-URL: Homepage, https://github.com/pattan-net/pattan-email
Project-URL: Documentation, https://github.com/pattan-net/pattan-email/docs
Keywords: pattan,sendgrid
Classifier: Programming Language :: Python :: 3
Classifier: License :: OSI Approved :: BSD License
Classifier: Operating System :: OS Independent
Requires-Python: >=3.10
License-File: LICENSE
Requires-Dist: sendgrid>=6.10.0
Requires-Dist: pydantic>=2.11.4
Dynamic: license-file
